{
  "data": {
    "article": {},
    "attachments": {},
    "author_id": "1971027114582474752",
    "conversation_id": "1983035671490306513",
    "created_at": "2025-10-28T07:54:24.000Z",
    "edit_controls": {
      "editable_until": "2025-10-28T08:54:24.000Z",
      "edits_remaining": 5,
      "is_edit_eligible": false
    },
    "edit_history_tweet_ids": [
      "1983079891173261564"
    ],
    "entities": {
      "mentions": [
        {
          "end": 7,
          "id": "1613079089879076864",
          "start": 0,
          "username": "Cldeop"
        }
      ]
    },
    "geo": {},
    "id": "1983079891173261564",
    "in_reply_to_user_id": "1613079089879076864",
    "lang": "zh",
    "note_tweet": {
      "entities": {}
    },
    "possibly_sensitive": false,
    "public_metrics": {
      "bookmark_count": 0,
      "impression_count": 0,
      "like_count": 0,
      "quote_count": 0,
      "reply_count": 0,
      "retweet_count": 0
    },
    "referenced_tweets": [
      {
        "id": "1983035671490306513",
        "type": "replied_to"
      }
    ],
    "reply_settings": "everyone",
    "text": "@Cldeop 相机吧"
  },
  "includes": {
    "media": [
      {
        "height": 1767,
        "media_key": "3_1983035665677008897",
        "public_metrics": {},
        "type": "photo",
        "url": "https://pbs.twimg.com/media/G4Uobm2bwAE7E3c.jpg",
        "width": 1115
      }
    ],
    "tweets": [
      {
        "article": {},
        "attachments": {},
        "author_id": "1971027114582474752",
        "conversation_id": "1983035671490306513",
        "created_at": "2025-10-28T07:54:24.000Z",
        "edit_controls": {
          "editable_until": "2025-10-28T08:54:24.000Z",
          "edits_remaining": 5,
          "is_edit_eligible": false
        },
        "edit_history_tweet_ids": [
          "1983079891173261564"
        ],
        "entities": {
          "mentions": [
            {
              "end": 7,
              "id": "1613079089879076864",
              "start": 0,
              "username": "Cldeop"
            }
          ]
        },
        "geo": {},
        "id": "1983079891173261564",
        "in_reply_to_user_id": "1613079089879076864",
        "lang": "zh",
        "note_tweet": {
          "entities": {}
        },
        "possibly_sensitive": false,
        "public_metrics": {
          "bookmark_count": 0,
          "impression_count": 0,
          "like_count": 0,
          "quote_count": 0,
          "reply_count": 0,
          "retweet_count": 0
        },
        "referenced_tweets": [
          {
            "id": "1983035671490306513",
            "type": "replied_to"
          }
        ],
        "reply_settings": "everyone",
        "text": "@Cldeop 相机吧"
      },
      {
        "article": {},
        "attachments": {
          "media_keys": [
            "3_1983035665677008897"
          ]
        },
        "author_id": "1613079089879076864",
        "conversation_id": "1983035671490306513",
        "created_at": "2025-10-28T04:58:41.000Z",
        "edit_controls": {
          "editable_until": "2025-10-28T05:58:41.000Z",
          "edits_remaining": 5,
          "is_edit_eligible": true
        },
        "edit_history_tweet_ids": [
          "1983035671490306513"
        ],
        "entities": {
          "urls": [
            {
              "display_url": "pic.x.com/fH5yjOOu8p",
              "end": 23,
              "expanded_url": "https://x.com/Cldeop/status/1983035671490306513/photo/1",
              "media_key": "3_1983035665677008897",
              "start": 0,
              "url": "https://t.co/fH5yjOOu8p"
            }
          ]
        },
        "geo": {},
        "id": "1983035671490306513",
        "lang": "zxx",
        "note_tweet": {
          "entities": {}
        },
        "possibly_sensitive": false,
        "public_metrics": {
          "bookmark_count": 12,
          "impression_count": 26674,
          "like_count": 332,
          "quote_count": 2,
          "reply_count": 29,
          "retweet_count": 5
        },
        "reply_settings": "everyone",
        "text": "https://t.co/fH5yjOOu8p"
      }
    ],
    "users": [
      {
        "created_at": "2025-09-25T01:41:12.000Z",
        "description": "=破滅/終焉之梦丨🇨🇳-廣東深圳丨音ゲー愛好者www 丨maimaiでらつくす16010rating丨CHUNITHM嘗試中…… ❗️丨私人委託開放中 丨是幻想成為制霸全音ゲー的神秘女子———Kanataqかなたく，參上！",
        "entities": {
          "url": {
            "urls": [
              {
                "display_url": "pixiv.net/users/120006350",
                "end": 23,
                "expanded_url": "https://www.pixiv.net/users/120006350",
                "start": 0,
                "url": "https://t.co/aKrTSIxeG5"
              }
            ]
          }
        },
        "id": "1971027114582474752",
        "location": "Yuen Long District, Hong Kong",
        "name": "破滅かなたく",
        "pinned_tweet_id": "1981615189167616428",
        "profile_image_url": "https://pbs.twimg.com/profile_images/1971027247466491904/xYqKzjYu_normal.jpg",
        "protected": false,
        "public_metrics": {
          "followers_count": 12,
          "following_count": 56,
          "like_count": 241,
          "listed_count": 0,
          "media_count": 26,
          "tweet_count": 141
        },
        "url": "https://t.co/aKrTSIxeG5",
        "username": "Kanataqqq0221",
        "verified": false
      },
      {
        "created_at": "2023-01-11T07:43:29.000Z",
        "description": "yún jiū｜くもはと\n推特𝕏 见证每一种生物\n生活号@ACldJP\n欢迎私信投稿",
        "entities": {
          "description": {
            "mentions": [
              {
                "end": 35,
                "start": 28,
                "username": "ACldJP"
              }
            ]
          }
        },
        "id": "1613079089879076864",
        "location": "点一下「查看更多」试试？",
        "name": "雲鳩",
        "pinned_tweet_id": "1950895151779561979",
        "profile_image_url": "https://pbs.twimg.com/profile_images/1976306297789370368/tQr5aNJl_normal.png",
        "protected": false,
        "public_metrics": {
          "followers_count": 85259,
          "following_count": 651,
          "like_count": 31178,
          "listed_count": 258,
          "media_count": 13019,
          "tweet_count": 18461
        },
        "username": "Cldeop",
        "verified": true
      }
    ]
  }
}