{
  "data": {
    "article": {},
    "attachments": {},
    "author_id": "1971027114582474752",
    "conversation_id": "2072709886220321096",
    "created_at": "2026-07-02T17:46:22.000Z",
    "edit_controls": {
      "editable_until": "2026-07-02T18:46:22.000Z",
      "edits_remaining": 5,
      "is_edit_eligible": false
    },
    "edit_history_tweet_ids": [
      "2072738668511728126"
    ],
    "entities": {
      "mentions": [
        {
          "end": 9,
          "id": "1463403514592333829",
          "start": 0,
          "username": "Y1103S86"
        }
      ]
    },
    "geo": {},
    "id": "2072738668511728126",
    "in_reply_to_user_id": "1463403514592333829",
    "lang": "ja",
    "note_tweet": {
      "entities": {}
    },
    "possibly_sensitive": false,
    "public_metrics": {
      "bookmark_count": 0,
      "impression_count": 0,
      "like_count": 0,
      "quote_count": 0,
      "reply_count": 0,
      "retweet_count": 0
    },
    "referenced_tweets": [
      {
        "id": "2072709886220321096",
        "type": "replied_to"
      }
    ],
    "reply_settings": "everyone",
    "text": "@Y1103S86 主人"
  },
  "includes": {
    "media": [
      {
        "height": 1920,
        "media_key": "3_2072709874757296128",
        "public_metrics": {},
        "type": "photo",
        "url": "https://pbs.twimg.com/media/HMO-pj9aYAAYuqa.jpg",
        "width": 1080
      },
      {
        "height": 1920,
        "media_key": "3_2072709881761828864",
        "public_metrics": {},
        "type": "photo",
        "url": "https://pbs.twimg.com/media/HMO-p-DbEAAwN8P.jpg",
        "width": 1440
      }
    ],
    "tweets": [
      {
        "article": {},
        "attachments": {},
        "author_id": "1971027114582474752",
        "conversation_id": "2072709886220321096",
        "created_at": "2026-07-02T17:46:22.000Z",
        "edit_controls": {
          "editable_until": "2026-07-02T18:46:22.000Z",
          "edits_remaining": 5,
          "is_edit_eligible": false
        },
        "edit_history_tweet_ids": [
          "2072738668511728126"
        ],
        "entities": {
          "mentions": [
            {
              "end": 9,
              "id": "1463403514592333829",
              "start": 0,
              "username": "Y1103S86"
            }
          ]
        },
        "geo": {},
        "id": "2072738668511728126",
        "in_reply_to_user_id": "1463403514592333829",
        "lang": "ja",
        "note_tweet": {
          "entities": {}
        },
        "possibly_sensitive": false,
        "public_metrics": {
          "bookmark_count": 0,
          "impression_count": 0,
          "like_count": 0,
          "quote_count": 0,
          "reply_count": 0,
          "retweet_count": 0
        },
        "referenced_tweets": [
          {
            "id": "2072709886220321096",
            "type": "replied_to"
          }
        ],
        "reply_settings": "everyone",
        "text": "@Y1103S86 主人"
      },
      {
        "article": {},
        "attachments": {
          "media_keys": [
            "3_2072709874757296128",
            "3_2072709881761828864"
          ]
        },
        "author_id": "1463403514592333829",
        "conversation_id": "2072709886220321096",
        "created_at": "2026-07-02T15:52:00.000Z",
        "edit_controls": {
          "editable_until": "2026-07-02T16:52:00.000Z",
          "edits_remaining": 5,
          "is_edit_eligible": true
        },
        "edit_history_tweet_ids": [
          "2072709886220321096"
        ],
        "entities": {
          "urls": [
            {
              "display_url": "pic.x.com/BV7QbvDWE5",
              "end": 28,
              "expanded_url": "https://x.com/Y1103S86/status/2072709886220321096/photo/1",
              "media_key": "3_2072709874757296128",
              "start": 5,
              "url": "https://t.co/BV7QbvDWE5"
            },
            {
              "display_url": "pic.x.com/BV7QbvDWE5",
              "end": 28,
              "expanded_url": "https://x.com/Y1103S86/status/2072709886220321096/photo/1",
              "media_key": "3_2072709881761828864",
              "start": 5,
              "url": "https://t.co/BV7QbvDWE5"
            }
          ]
        },
        "geo": {},
        "id": "2072709886220321096",
        "lang": "en",
        "note_tweet": {
          "entities": {}
        },
        "possibly_sensitive": false,
        "public_metrics": {
          "bookmark_count": 0,
          "impression_count": 262,
          "like_count": 5,
          "quote_count": 0,
          "reply_count": 1,
          "retweet_count": 0
        },
        "reply_settings": "everyone",
        "text": "ootd https://t.co/BV7QbvDWE5"
      }
    ],
    "users": [
      {
        "created_at": "2025-09-25T01:41:12.000Z",
        "description": "=破滅/神月丨♀丨17歲の音ゲーマ、音ゲー関連のイラストを描いてるよ^^丨スシロー賽高丨中文&日本語⭕️英語❌丨maimaiでらっくす16217丨 彼氏@TORLI114514 丨逃生艙@Kanataqqq9178丨OC相關投稿➡️#Kam1zuk1_art",
        "entities": {
          "description": {
            "hashtags": [
              {
                "end": 129,
                "start": 116,
                "tag": "Kam1zuk1_art"
              }
            ],
            "mentions": [
              {
                "end": 88,
                "start": 76,
                "username": "TORLI114514"
              },
              {
                "end": 107,
                "start": 93,
                "username": "Kanataqqq9178"
              }
            ]
          },
          "url": {
            "urls": [
              {
                "display_url": "pixiv.net/users/120006350",
                "end": 23,
                "expanded_url": "https://www.pixiv.net/users/120006350",
                "start": 0,
                "url": "https://t.co/aKrTSIxMvD"
              }
            ]
          }
        },
        "id": "1971027114582474752",
        "location": "破滅の部屋",
        "name": "Kanataqかなたく＊滅3rdBOT",
        "pinned_tweet_id": "2059089706206605366",
        "profile_image_url": "https://pbs.twimg.com/profile_images/2054826581827502080/UAI3TenM_normal.jpg",
        "protected": false,
        "public_metrics": {
          "followers_count": 756,
          "following_count": 364,
          "like_count": 2823,
          "listed_count": 5,
          "media_count": 366,
          "tweet_count": 2038
        },
        "url": "https://t.co/aKrTSIxMvD",
        "username": "Kanataqqq0221",
        "verified": false
      },
      {
        "created_at": "2021-11-24T07:06:37.000Z",
        "description": "一个之前存在过的人 不会再混之前的任何圈子\nDom /有老婆\n🚪198 私聊只回复正常问题口令红包（我也没逼你过）",
        "id": "1463403514592333829",
        "location": "🚪198 288 568 ",
        "name": "姜川",
        "pinned_tweet_id": "2063423226286571891",
        "profile_image_url": "https://pbs.twimg.com/profile_images/2061655197731147776/TqygjwsB_normal.jpg",
        "protected": false,
        "public_metrics": {
          "followers_count": 6881,
          "following_count": 224,
          "like_count": 2178,
          "listed_count": 14,
          "media_count": 310,
          "tweet_count": 2316
        },
        "url": "",
        "username": "Y1103S86",
        "verified": false
      }
    ]
  }
}