{
  "data": {
    "article": {},
    "attachments": {},
    "author_id": "1971027114582474752",
    "conversation_id": "2028983576168194485",
    "created_at": "2026-03-04T04:58:03.000Z",
    "edit_controls": {
      "editable_until": "2026-03-04T05:58:03.000Z",
      "edits_remaining": 5,
      "is_edit_eligible": false
    },
    "edit_history_tweet_ids": [
      "2029058771763511336"
    ],
    "entities": {
      "mentions": [
        {
          "end": 10,
          "id": "1777344951556456448",
          "start": 0,
          "username": "AyakoHimy"
        },
        {
          "end": 25,
          "id": "2006891438332952576",
          "start": 11,
          "username": "Kanataqqq9178"
        }
      ]
    },
    "geo": {},
    "id": "2029058771763511336",
    "in_reply_to_user_id": "1777344951556456448",
    "lang": "und",
    "note_tweet": {
      "entities": {}
    },
    "possibly_sensitive": false,
    "public_metrics": {
      "bookmark_count": 0,
      "impression_count": 0,
      "like_count": 0,
      "quote_count": 0,
      "reply_count": 0,
      "retweet_count": 0
    },
    "referenced_tweets": [
      {
        "id": "2029054873438961936",
        "type": "replied_to"
      }
    ],
    "reply_settings": "everyone",
    "text": "@AyakoHimy @Kanataqqq9178 OvO"
  },
  "includes": {
    "tweets": [
      {
        "article": {},
        "attachments": {},
        "author_id": "1971027114582474752",
        "conversation_id": "2028983576168194485",
        "created_at": "2026-03-04T04:58:03.000Z",
        "edit_controls": {
          "editable_until": "2026-03-04T05:58:03.000Z",
          "edits_remaining": 5,
          "is_edit_eligible": false
        },
        "edit_history_tweet_ids": [
          "2029058771763511336"
        ],
        "entities": {
          "mentions": [
            {
              "end": 10,
              "id": "1777344951556456448",
              "start": 0,
              "username": "AyakoHimy"
            },
            {
              "end": 25,
              "id": "2006891438332952576",
              "start": 11,
              "username": "Kanataqqq9178"
            }
          ]
        },
        "geo": {},
        "id": "2029058771763511336",
        "in_reply_to_user_id": "1777344951556456448",
        "lang": "und",
        "note_tweet": {
          "entities": {}
        },
        "possibly_sensitive": false,
        "public_metrics": {
          "bookmark_count": 0,
          "impression_count": 0,
          "like_count": 0,
          "quote_count": 0,
          "reply_count": 0,
          "retweet_count": 0
        },
        "referenced_tweets": [
          {
            "id": "2029054873438961936",
            "type": "replied_to"
          }
        ],
        "reply_settings": "everyone",
        "text": "@AyakoHimy @Kanataqqq9178 OvO"
      },
      {
        "article": {},
        "attachments": {},
        "author_id": "1777344951556456448",
        "conversation_id": "2028983576168194485",
        "created_at": "2026-03-04T04:42:34.000Z",
        "edit_controls": {
          "editable_until": "2026-03-04T05:42:34.000Z",
          "edits_remaining": 5,
          "is_edit_eligible": false
        },
        "edit_history_tweet_ids": [
          "2029054873438961936"
        ],
        "entities": {
          "mentions": [
            {
              "end": 14,
              "id": "1971027114582474752",
              "start": 0,
              "username": "Kanataqqq0221"
            },
            {
              "end": 29,
              "id": "2006891438332952576",
              "start": 15,
              "username": "Kanataqqq9178"
            }
          ]
        },
        "geo": {},
        "id": "2029054873438961936",
        "in_reply_to_user_id": "1971027114582474752",
        "lang": "und",
        "note_tweet": {
          "entities": {}
        },
        "possibly_sensitive": false,
        "public_metrics": {
          "bookmark_count": 0,
          "impression_count": 5,
          "like_count": 1,
          "quote_count": 0,
          "reply_count": 1,
          "retweet_count": 0
        },
        "referenced_tweets": [
          {
            "id": "2028983576168194485",
            "type": "replied_to"
          }
        ],
        "reply_settings": "everyone",
        "text": "@Kanataqqq0221 @Kanataqqq9178 OwO"
      }
    ],
    "users": [
      {
        "created_at": "2025-09-25T01:41:12.000Z",
        "derived": {
          "locations": [
            {
              "country_code": "HK",
              "full_name": "Yuen Long, Hong Kong",
              "geo": {
                "coordinates": [
                  114.05,
                  22.41667
                ],
                "type": "Point"
              },
              "region": "Yuen Long"
            }
          ]
        },
        "description": "=破滅/終焉之梦丨16歲の音ゲーマ～音ゲー関連のイラストを描いてるよ^^ もう～みんなに気に入ってもらえるといいな！丨中文&日本語OK 英語苦手丨maimaiでらつくす16128 丨DM🆗丨精神不安定QvQ互fo大歡迎ww丨 @TORLI114514 大好きです〜丨轉生@Kanataqqq9178",
        "entities": {
          "description": {
            "mentions": [
              {
                "end": 125,
                "start": 113,
                "username": "TORLI114514"
              },
              {
                "end": 149,
                "start": 135,
                "username": "Kanataqqq9178"
              }
            ]
          },
          "url": {
            "urls": [
              {
                "display_url": "pixiv.net/users/120006350",
                "end": 23,
                "expanded_url": "https://www.pixiv.net/users/120006350",
                "start": 0,
                "url": "https://t.co/aKrTSIxeG5"
              }
            ]
          }
        },
        "id": "1971027114582474752",
        "location": "Yuen Long District, Hong Kong",
        "name": "破滅かなたく(はーめつ)",
        "pinned_tweet_id": "2021830168860586310",
        "profile_image_url": "https://pbs.twimg.com/profile_images/2027893096135184384/qVxIiyua_normal.jpg",
        "protected": false,
        "public_metrics": {
          "followers_count": 222,
          "following_count": 137,
          "like_count": 811,
          "listed_count": 3,
          "media_count": 156,
          "tweet_count": 667
        },
        "url": "https://t.co/aKrTSIxeG5",
        "username": "Kanataqqq0221",
        "verified": false
      },
      {
        "created_at": "2024-04-08T14:37:27.000Z",
        "description": "24/06 21/01 私はフリーランスの作曲家兼画家です\n\nこの文章を読んでくださっているあなたと、ぜひ音楽でコラボレーションしたいです。\n\nここでは誰も私を知らないので、他のソーシャル メディア プラットフォームよりも自然に自分の日常生活や仕事をシェアしています。",
        "id": "1777344951556456448",
        "name": "ayako himy",
        "pinned_tweet_id": "2015734311144833070",
        "profile_image_url": "https://pbs.twimg.com/profile_images/2022891768249987072/0Ppo8nbW_normal.jpg",
        "protected": false,
        "public_metrics": {
          "followers_count": 26,
          "following_count": 70,
          "like_count": 443,
          "listed_count": 0,
          "media_count": 84,
          "tweet_count": 1225
        },
        "username": "AyakoHimy",
        "verified": false
      },
      {
        "created_at": "2026-01-02T00:53:13.000Z",
        "description": "=終焉之梦Kanataq/破滅 maimai/SDVX/CHUNITHM/ONGEKI 廣深港通勤 喜欢请关注我（輪迴轉生三號機）",
        "id": "2006891438332952576",
        "location": "Hong Kong",
        "name": "Kanataqかなたく",
        "profile_image_url": "https://pbs.twimg.com/profile_images/2006891623628820480/ByCar8cq_normal.jpg",
        "protected": false,
        "public_metrics": {
          "followers_count": 17,
          "following_count": 46,
          "like_count": 28,
          "listed_count": 0,
          "media_count": 9,
          "tweet_count": 25
        },
        "username": "Kanataqqq9178",
        "verified": false
      }
    ]
  }
}