{
  "data": {
    "article": {},
    "attachments": {},
    "author_id": "1971027114582474752",
    "conversation_id": "2034943782534488458",
    "created_at": "2026-03-21T14:14:49.000Z",
    "edit_controls": {
      "editable_until": "2026-03-21T15:14:49.000Z",
      "edits_remaining": 5,
      "is_edit_eligible": false
    },
    "edit_history_tweet_ids": [
      "2035359479676727458"
    ],
    "entities": {
      "mentions": [
        {
          "end": 10,
          "id": "1502506015350087680",
          "start": 0,
          "username": "LSark1120"
        }
      ]
    },
    "geo": {},
    "id": "2035359479676727458",
    "in_reply_to_user_id": "1502506015350087680",
    "lang": "zh",
    "note_tweet": {
      "entities": {}
    },
    "possibly_sensitive": false,
    "public_metrics": {
      "bookmark_count": 0,
      "impression_count": 0,
      "like_count": 0,
      "quote_count": 0,
      "reply_count": 0,
      "retweet_count": 0
    },
    "referenced_tweets": [
      {
        "id": "2035256802355581031",
        "type": "replied_to"
      }
    ],
    "reply_settings": "everyone",
    "text": "@LSark1120 жйЂтЊдтЊдтЊдтЊдтЊдтЊд"
  },
  "includes": {
    "tweets": [
      {
        "article": {},
        "attachments": {},
        "author_id": "1971027114582474752",
        "conversation_id": "2034943782534488458",
        "created_at": "2026-03-21T14:14:49.000Z",
        "edit_controls": {
          "editable_until": "2026-03-21T15:14:49.000Z",
          "edits_remaining": 5,
          "is_edit_eligible": false
        },
        "edit_history_tweet_ids": [
          "2035359479676727458"
        ],
        "entities": {
          "mentions": [
            {
              "end": 10,
              "id": "1502506015350087680",
              "start": 0,
              "username": "LSark1120"
            }
          ]
        },
        "geo": {},
        "id": "2035359479676727458",
        "in_reply_to_user_id": "1502506015350087680",
        "lang": "zh",
        "note_tweet": {
          "entities": {}
        },
        "possibly_sensitive": false,
        "public_metrics": {
          "bookmark_count": 0,
          "impression_count": 0,
          "like_count": 0,
          "quote_count": 0,
          "reply_count": 0,
          "retweet_count": 0
        },
        "referenced_tweets": [
          {
            "id": "2035256802355581031",
            "type": "replied_to"
          }
        ],
        "reply_settings": "everyone",
        "text": "@LSark1120 жйЂтЊдтЊдтЊдтЊдтЊдтЊд"
      },
      {
        "article": {},
        "attachments": {},
        "author_id": "1502506015350087680",
        "conversation_id": "2034943782534488458",
        "created_at": "2026-03-21T07:26:49.000Z",
        "edit_controls": {
          "editable_until": "2026-03-21T08:26:49.000Z",
          "edits_remaining": 5,
          "is_edit_eligible": false
        },
        "edit_history_tweet_ids": [
          "2035256802355581031"
        ],
        "entities": {
          "mentions": [
            {
              "end": 14,
              "id": "1971027114582474752",
              "start": 0,
              "username": "Kanataqqq0221"
            }
          ]
        },
        "geo": {},
        "id": "2035256802355581031",
        "in_reply_to_user_id": "1971027114582474752",
        "lang": "ja",
        "note_tweet": {
          "entities": {}
        },
        "possibly_sensitive": false,
        "public_metrics": {
          "bookmark_count": 0,
          "impression_count": 3,
          "like_count": 0,
          "quote_count": 0,
          "reply_count": 0,
          "retweet_count": 0
        },
        "referenced_tweets": [
          {
            "id": "2034943782534488458",
            "type": "replied_to"
          }
        ],
        "reply_settings": "everyone",
        "text": "@Kanataqqq0221 тЊдтЊдтЊдтЊдтЊдтЊдтЊдтЊдтЊд"
      }
    ],
    "users": [
      {
        "created_at": "2025-09-25T01:41:12.000Z",
        "derived": {
          "locations": [
            {
              "country_code": "HK",
              "full_name": "Yuen Long, Hong Kong",
              "geo": {
                "coordinates": [
                  114.05,
                  22.41667
                ],
                "type": "Point"
              },
              "region": "Yuen Long"
            }
          ]
        },
        "description": "=уа┤Т╗Ё/ухѓуёЅС╣ІТбдСИе16ТГ▓сЂ«жЪ│сѓ▓сЃ╝сЃъ№йъжЪ│сѓ▓сЃ╝жќбжђБсЂ«сѓцсЃЕсѓ╣сЃѕсѓњТЈЈсЂёсЂдсѓІсѓѕ^^СИесѓ╣сѓисЃГсЃ╝У│йжФўСИеСИГТќЄ&ТЌЦТюгУфъРГЋ№ИЈУІ▒УфъРЮїСИеmaimaiсЂДсѓЅсЂцсЂЈсЂЎ16153СИеDM­ЪєЌСИеС║њfoтцДТГАУ┐јwwСИе @TORLI114514 тцДтЦйсЂЇсЂДсЂЎсђюСИежђЃућЪУЅЎ@Kanataqqq9178",
        "entities": {
          "description": {
            "mentions": [
              {
                "end": 99,
                "start": 87,
                "username": "TORLI114514"
              },
              {
                "end": 124,
                "start": 110,
                "username": "Kanataqqq9178"
              }
            ]
          },
          "url": {
            "urls": [
              {
                "display_url": "pixiv.net/users/120006350",
                "end": 23,
                "expanded_url": "https://www.pixiv.net/users/120006350",
                "start": 0,
                "url": "https://t.co/aKrTSIxMvD"
              }
            ]
          }
        },
        "id": "1971027114582474752",
        "location": "Yuen Long District, Hong Kong",
        "name": "уа┤Т╗ЁсЂІсЂфсЂЪсЂЈ(сЂ»сЃ╝сѓЂсЂц)",
        "pinned_tweet_id": "2029721775060439205",
        "profile_image_url": "https://pbs.twimg.com/profile_images/2027893096135184384/qVxIiyua_normal.jpg",
        "protected": false,
        "public_metrics": {
          "followers_count": 302,
          "following_count": 170,
          "like_count": 1202,
          "listed_count": 3,
          "media_count": 195,
          "tweet_count": 926
        },
        "url": "https://t.co/aKrTSIxMvD",
        "username": "Kanataqqq0221",
        "verified": false
      },
      {
        "created_at": "2022-03-12T04:45:39.000Z",
        "description": "СйатЦй",
        "entities": {
          "url": {
            "urls": [
              {
                "display_url": "b23.tv/g1OEToG",
                "end": 23,
                "expanded_url": "https://b23.tv/g1OEToG",
                "start": 0,
                "url": "https://t.co/mkENe6xwEv"
              }
            ]
          }
        },
        "id": "1502506015350087680",
        "location": "тюеСйат┐ЃжЄїРЮц№ИЈ",
        "name": "Т│аТ«Є_Eric",
        "pinned_tweet_id": "1686053477649387520",
        "profile_image_url": "https://pbs.twimg.com/profile_images/1753029449581572096/rbEOn5HS_normal.jpg",
        "protected": false,
        "public_metrics": {
          "followers_count": 160,
          "following_count": 441,
          "like_count": 4047,
          "listed_count": 0,
          "media_count": 41,
          "tweet_count": 321
        },
        "url": "https://t.co/mkENe6xwEv",
        "username": "LSark1120",
        "verified": false
      }
    ]
  }
}