{
  "data": {
    "article": {},
    "attachments": {},
    "author_id": "1971027114582474752",
    "conversation_id": "2061562960439603617",
    "created_at": "2026-06-03T05:38:33.000Z",
    "edit_controls": {
      "editable_until": "2026-06-03T06:38:33.000Z",
      "edits_remaining": 5,
      "is_edit_eligible": false
    },
    "edit_history_tweet_ids": [
      "2062046256407716320"
    ],
    "entities": {
      "mentions": [
        {
          "end": 12,
          "id": "1761282483834998784",
          "start": 0,
          "username": "qiancongxyn"
        }
      ]
    },
    "geo": {},
    "id": "2062046256407716320",
    "in_reply_to_user_id": "1761282483834998784",
    "lang": "und",
    "note_tweet": {
      "entities": {}
    },
    "possibly_sensitive": false,
    "public_metrics": {
      "bookmark_count": 0,
      "impression_count": 0,
      "like_count": 0,
      "quote_count": 0,
      "reply_count": 0,
      "retweet_count": 0
    },
    "referenced_tweets": [
      {
        "id": "2061562960439603617",
        "type": "replied_to"
      }
    ],
    "reply_settings": "everyone",
    "text": "@qiancongxyn xm"
  },
  "includes": {
    "media": [
      {
        "height": 1183,
        "media_key": "3_2061562931687661568",
        "public_metrics": {},
        "type": "photo",
        "url": "https://pbs.twimg.com/media/HJwkkFFbIAAeNwH.jpg",
        "width": 506
      }
    ],
    "tweets": [
      {
        "article": {},
        "attachments": {},
        "author_id": "1971027114582474752",
        "conversation_id": "2061562960439603617",
        "created_at": "2026-06-03T05:38:33.000Z",
        "edit_controls": {
          "editable_until": "2026-06-03T06:38:33.000Z",
          "edits_remaining": 5,
          "is_edit_eligible": false
        },
        "edit_history_tweet_ids": [
          "2062046256407716320"
        ],
        "entities": {
          "mentions": [
            {
              "end": 12,
              "id": "1761282483834998784",
              "start": 0,
              "username": "qiancongxyn"
            }
          ]
        },
        "geo": {},
        "id": "2062046256407716320",
        "in_reply_to_user_id": "1761282483834998784",
        "lang": "und",
        "note_tweet": {
          "entities": {}
        },
        "possibly_sensitive": false,
        "public_metrics": {
          "bookmark_count": 0,
          "impression_count": 0,
          "like_count": 0,
          "quote_count": 0,
          "reply_count": 0,
          "retweet_count": 0
        },
        "referenced_tweets": [
          {
            "id": "2061562960439603617",
            "type": "replied_to"
          }
        ],
        "reply_settings": "everyone",
        "text": "@qiancongxyn xm"
      },
      {
        "article": {},
        "attachments": {
          "media_keys": [
            "3_2061562931687661568"
          ]
        },
        "author_id": "1761282483834998784",
        "conversation_id": "2061562960439603617",
        "created_at": "2026-06-01T21:38:06.000Z",
        "edit_controls": {
          "editable_until": "2026-06-01T22:38:06.000Z",
          "edits_remaining": 5,
          "is_edit_eligible": true
        },
        "edit_history_tweet_ids": [
          "2061562960439603617"
        ],
        "entities": {
          "urls": [
            {
              "display_url": "pic.x.com/IZGEJVLcvd",
              "end": 29,
              "expanded_url": "https://x.com/qiancongxyn/status/2061562960439603617/photo/1",
              "media_key": "3_2061562931687661568",
              "start": 6,
              "url": "https://t.co/IZGEJVLcvd"
            }
          ]
        },
        "geo": {},
        "id": "2061562960439603617",
        "lang": "zh",
        "note_tweet": {
          "entities": {}
        },
        "possibly_sensitive": false,
        "public_metrics": {
          "bookmark_count": 6,
          "impression_count": 16688,
          "like_count": 150,
          "quote_count": 1,
          "reply_count": 38,
          "retweet_count": 3
        },
        "reply_settings": "everyone",
        "text": "这话说的😨 https://t.co/IZGEJVLcvd"
      }
    ],
    "users": [
      {
        "created_at": "2025-09-25T01:41:12.000Z",
        "description": "=破滅/神月丨♀丨16歲の音ゲーマ、音ゲー関連のイラストを描いてるよ^^丨スシロー賽高丨中文&日本語⭕️英語❌丨maimaiでらっくす16217丨 彼氏@TORLI114514 丨逃生艙@Kanataqqq9178丨OC相關投稿➡️#Kam1zuk1_art",
        "entities": {
          "description": {
            "hashtags": [
              {
                "end": 129,
                "start": 116,
                "tag": "Kam1zuk1_art"
              }
            ],
            "mentions": [
              {
                "end": 88,
                "start": 76,
                "username": "TORLI114514"
              },
              {
                "end": 107,
                "start": 93,
                "username": "Kanataqqq9178"
              }
            ]
          },
          "url": {
            "urls": [
              {
                "display_url": "pixiv.net/users/120006350",
                "end": 23,
                "expanded_url": "https://www.pixiv.net/users/120006350",
                "start": 0,
                "url": "https://t.co/aKrTSIxMvD"
              }
            ]
          }
        },
        "id": "1971027114582474752",
        "location": "破滅の部屋",
        "name": "Kanataqかなたく＊滅3rdBOT",
        "pinned_tweet_id": "2059089706206605366",
        "profile_image_url": "https://pbs.twimg.com/profile_images/2054826581827502080/UAI3TenM_normal.jpg",
        "protected": false,
        "public_metrics": {
          "followers_count": 619,
          "following_count": 285,
          "like_count": 2494,
          "listed_count": 4,
          "media_count": 323,
          "tweet_count": 1820
        },
        "url": "https://t.co/aKrTSIxMvD",
        "username": "Kanataqqq0221",
        "verified": false
      },
      {
        "created_at": "2024-02-24T06:51:06.000Z",
        "description": "mtf｜🍥 HRT 26.2.21｜无证含糖\n出厂日期 09.3.14\n\n已炸柜｜家暴党｜😭 断糖 26.5.26\n高二物化生｜成绩倒数｜考虑休学\n爱哭+发牢骚｜负面帖垃圾桶｜觉得我傻逼就ban我\n不阔爱不pass｜缺爱想交朋友\n\n私信互fo｜友好相处｜喜欢我就关注下呗🥺\n对象 @xiaoyimiaoaaa",
        "entities": {
          "description": {
            "mentions": [
              {
                "end": 154,
                "start": 140,
                "username": "xiaoyimiaoaaa"
              }
            ]
          },
          "url": {
            "urls": [
              {
                "display_url": "ngl.link/water14008",
                "end": 23,
                "expanded_url": "http://ngl.link/water14008",
                "start": 0,
                "url": "https://t.co/e8l2h7lQ53"
              }
            ]
          }
        },
        "id": "1761282483834998784",
        "location": "土卫二",
        "name": "浅葱🍥🏳️‍⚧️",
        "pinned_tweet_id": "2060573450616664245",
        "profile_image_url": "https://pbs.twimg.com/profile_images/2057460306365087744/QGhTRD4k_normal.jpg",
        "protected": false,
        "public_metrics": {
          "followers_count": 1586,
          "following_count": 906,
          "like_count": 1585,
          "listed_count": 2,
          "media_count": 89,
          "tweet_count": 1387
        },
        "url": "https://t.co/e8l2h7lQ53",
        "username": "qiancongxyn",
        "verified": true
      }
    ]
  }
}