{
  "data": {
    "article": {},
    "attachments": {},
    "author_id": "1971027114582474752",
    "conversation_id": "2021158221776306191",
    "created_at": "2026-02-11T08:12:58.000Z",
    "edit_controls": {
      "editable_until": "2026-02-11T09:12:58.000Z",
      "edits_remaining": 5,
      "is_edit_eligible": false
    },
    "edit_history_tweet_ids": [
      "2021497678237249924"
    ],
    "entities": {
      "mentions": [
        {
          "end": 15,
          "id": "2012867962596884480",
          "start": 0,
          "username": "Oblivious64756"
        },
        {
          "end": 28,
          "id": "1859254891971313665",
          "start": 16,
          "username": "dongmugen08"
        }
      ]
    },
    "geo": {},
    "id": "2021497678237249924",
    "in_reply_to_user_id": "2012867962596884480",
    "lang": "zh",
    "note_tweet": {
      "entities": {}
    },
    "possibly_sensitive": false,
    "public_metrics": {
      "bookmark_count": 0,
      "impression_count": 0,
      "like_count": 0,
      "quote_count": 0,
      "reply_count": 0,
      "retweet_count": 0
    },
    "referenced_tweets": [
      {
        "id": "2021497156105011212",
        "type": "replied_to"
      }
    ],
    "reply_settings": "everyone",
    "text": "@Oblivious64756 @dongmugen08 哎喲我滴媽"
  },
  "includes": {
    "tweets": [
      {
        "article": {},
        "attachments": {},
        "author_id": "1971027114582474752",
        "conversation_id": "2021158221776306191",
        "created_at": "2026-02-11T08:12:58.000Z",
        "edit_controls": {
          "editable_until": "2026-02-11T09:12:58.000Z",
          "edits_remaining": 5,
          "is_edit_eligible": false
        },
        "edit_history_tweet_ids": [
          "2021497678237249924"
        ],
        "entities": {
          "mentions": [
            {
              "end": 15,
              "id": "2012867962596884480",
              "start": 0,
              "username": "Oblivious64756"
            },
            {
              "end": 28,
              "id": "1859254891971313665",
              "start": 16,
              "username": "dongmugen08"
            }
          ]
        },
        "geo": {},
        "id": "2021497678237249924",
        "in_reply_to_user_id": "2012867962596884480",
        "lang": "zh",
        "note_tweet": {
          "entities": {}
        },
        "possibly_sensitive": false,
        "public_metrics": {
          "bookmark_count": 0,
          "impression_count": 0,
          "like_count": 0,
          "quote_count": 0,
          "reply_count": 0,
          "retweet_count": 0
        },
        "referenced_tweets": [
          {
            "id": "2021497156105011212",
            "type": "replied_to"
          }
        ],
        "reply_settings": "everyone",
        "text": "@Oblivious64756 @dongmugen08 哎喲我滴媽"
      },
      {
        "article": {},
        "attachments": {},
        "author_id": "2012867962596884480",
        "conversation_id": "2021158221776306191",
        "created_at": "2026-02-11T08:10:54.000Z",
        "edit_controls": {
          "editable_until": "2026-02-11T09:10:54.000Z",
          "edits_remaining": 5,
          "is_edit_eligible": false
        },
        "edit_history_tweet_ids": [
          "2021497156105011212"
        ],
        "entities": {
          "mentions": [
            {
              "end": 14,
              "id": "1971027114582474752",
              "start": 0,
              "username": "Kanataqqq0221"
            },
            {
              "end": 27,
              "id": "1859254891971313665",
              "start": 15,
              "username": "dongmugen08"
            }
          ]
        },
        "geo": {},
        "id": "2021497156105011212",
        "in_reply_to_user_id": "1971027114582474752",
        "lang": "ja",
        "note_tweet": {
          "entities": {}
        },
        "possibly_sensitive": false,
        "public_metrics": {
          "bookmark_count": 0,
          "impression_count": 2,
          "like_count": 1,
          "quote_count": 0,
          "reply_count": 1,
          "retweet_count": 0
        },
        "referenced_tweets": [
          {
            "id": "2021426805509627924",
            "type": "replied_to"
          }
        ],
        "reply_settings": "everyone",
        "text": "@Kanataqqq0221 @dongmugen08 666小號刷到你了"
      }
    ],
    "users": [
      {
        "created_at": "2025-09-25T01:41:12.000Z",
        "derived": {
          "locations": [
            {
              "country_code": "HK",
              "full_name": "Yuen Long, Hong Kong",
              "geo": {
                "coordinates": [
                  114.05,
                  22.41667
                ],
                "type": "Point"
              },
              "region": "Yuen Long"
            }
          ]
        },
        "description": "=破滅/終焉之梦丨16歲の音ゲーマ～音ゲー関連のイラストを描いてるよ^^ もう〜何でも描いてみるよ！みんなに気に入ってもらえるといいな！丨中文&日本語OK 英語苦手丨maimaiでらつくす16062丨精神不安定QvQ互fo大歡迎ww丨 @TORLI114514 大好きです〜丨轉生@Kanataqqq9178",
        "entities": {
          "description": {
            "mentions": [
              {
                "end": 130,
                "start": 118,
                "username": "TORLI114514"
              },
              {
                "end": 154,
                "start": 140,
                "username": "Kanataqqq9178"
              }
            ]
          },
          "url": {
            "urls": [
              {
                "display_url": "pixiv.net/users/120006350",
                "end": 23,
                "expanded_url": "https://www.pixiv.net/users/120006350",
                "start": 0,
                "url": "https://t.co/aKrTSIxMvD"
              }
            ]
          }
        },
        "id": "1971027114582474752",
        "location": "Yuen Long District, Hong Kong",
        "name": "破滅かなたく(はーめつ)",
        "pinned_tweet_id": "2016420726807658879",
        "profile_image_url": "https://pbs.twimg.com/profile_images/2011326629763821568/Y7oOHTW9_normal.jpg",
        "protected": false,
        "public_metrics": {
          "followers_count": 198,
          "following_count": 133,
          "like_count": 538,
          "listed_count": 3,
          "media_count": 95,
          "tweet_count": 444
        },
        "url": "https://t.co/aKrTSIxMvD",
        "username": "Kanataqqq0221",
        "verified": false
      },
      {
        "created_at": "2026-01-18T12:41:51.000Z",
        "description": "這是一個自我介紹～",
        "id": "2012867962596884480",
        "location": "Houston, TX",
        "name": "Oblivious",
        "profile_image_url": "https://pbs.twimg.com/profile_images/2013489676074532865/PrNRic15_normal.jpg",
        "protected": false,
        "public_metrics": {
          "followers_count": 1,
          "following_count": 101,
          "like_count": 11,
          "listed_count": 0,
          "media_count": 0,
          "tweet_count": 2
        },
        "username": "Oblivious64756",
        "verified": false
      },
      {
        "created_at": "2024-11-20T15:18:40.000Z",
        "description": "幸福的活下去吧",
        "entities": {
          "url": {
            "urls": [
              {
                "display_url": "ngl.link/dongmugen",
                "end": 23,
                "expanded_url": "https://ngl.link/dongmugen",
                "start": 0,
                "url": "https://t.co/bFjIvxeqO1"
              }
            ]
          }
        },
        "id": "1859254891971313665",
        "location": "斯德哥尔摩",
        "name": "东木艮",
        "pinned_tweet_id": "2014950901824553077",
        "profile_image_url": "https://pbs.twimg.com/profile_images/2004987018967937024/XHErfR23_normal.jpg",
        "protected": false,
        "public_metrics": {
          "followers_count": 1268,
          "following_count": 645,
          "like_count": 3474,
          "listed_count": 2,
          "media_count": 248,
          "tweet_count": 1664
        },
        "url": "https://t.co/bFjIvxeqO1",
        "username": "dongmugen08",
        "verified": false
      }
    ]
  }
}